[
  {
    "id": "linux-starter",
    "title": "從 Windows 開始學 Linux",
    "subtitle": "用 WSL2 建立第一個穩定的 Linux 學習環境",
    "author": "Happy eBook 編輯部",
    "category": "Linux 入門",
    "type": "web",
    "format": "網頁版 / PDF",
    "cover": "../assets/images/book-linux-starter.svg",
    "description": "用最少阻力開始學 Linux，從安裝、指令、工作流程一路到實作。",
    "downloadUrl": "",
    "buyUrl": "",
    "readUrl": "book.html?id=linux-starter",
    "featured": true,
    "popular": true,
    "priceLabel": "免費閱讀"
  },
  {
    "id": "epub-writing-guide",
    "title": "EPUB 製作實戰手冊",
    "subtitle": "從內容整理到上架格式，一次掌握電子書製作流程",
    "author": "林書晨",
    "category": "出版製作",
    "type": "paid",
    "format": "EPUB / PDF",
    "cover": "../assets/images/book-epub-guide.svg",
    "description": "適合想把文章、教材或課程筆記整理成正式電子書的創作者。",
    "downloadUrl": "",
    "buyUrl": "#buy-epub-writing-guide",
    "readUrl": "",
    "featured": true,
    "popular": false,
    "priceLabel": "付費購買"
  },
  {
    "id": "web-book-design",
    "title": "網頁版電子書設計筆記",
    "subtitle": "把靜態內容做成舒服好讀的 Web Book",
    "author": "周映青",
    "category": "前端設計",
    "type": "free",
    "format": "PDF / 原始檔",
    "cover": "../assets/images/book-web-design.svg",
    "description": "整理電子書版面、章節導覽、排版系統與閱讀體驗的設計思路。",
    "downloadUrl": "#download-web-book-design",
    "buyUrl": "",
    "readUrl": "",
    "featured": false,
    "popular": true,
    "priceLabel": "免費下載"
  },
  {
    "id": "teacher-digital-class",
    "title": "教師的數位教材工作流",
    "subtitle": "把講義、投影片與延伸閱讀整理成持續更新的內容平台",
    "author": "陳雅茹",
    "category": "教學應用",
    "type": "paid",
    "format": "PDF / 範本包",
    "cover": "../assets/images/book-teacher-digital.svg",
    "description": "面向教師與教育工作者，從內容拆解到教學平台建置的完整思路。",
    "downloadUrl": "",
    "buyUrl": "#buy-teacher-digital-class",
    "readUrl": "",
    "featured": false,
    "popular": true,
    "priceLabel": "付費購買"
  }
]

